{
  "success": true,
  "data": {
    "batchcomplete": "",
    "query": {
      "pages": {
        "15900022": {
          "pageid": 15900022,
          "ns": 0,
          "title": "A1689-zD1",
          "links": [
            {
              "ns": 0,
              "title": "NGC 5335"
            },
            {
              "ns": 0,
              "title": "NGC 5343"
            },
            {
              "ns": 0,
              "title": "NGC 5363"
            },
            {
              "ns": 0,
              "title": "NGC 5364"
            },
            {
              "ns": 0,
              "title": "NGC 5374"
            },
            {
              "ns": 0,
              "title": "NGC 5384"
            },
            {
              "ns": 0,
              "title": "NGC 5442"
            },
            {
              "ns": 0,
              "title": "NGC 5468"
            },
            {
              "ns": 0,
              "title": "NGC 5470"
            },
            {
              "ns": 0,
              "title": "NGC 5493"
            },
            {
              "ns": 0,
              "title": "NGC 5501"
            },
            {
              "ns": 0,
              "title": "NGC 5506"
            },
            {
              "ns": 0,
              "title": "NGC 5555"
            },
            {
              "ns": 0,
              "title": "NGC 5566"
            },
            {
              "ns": 0,
              "title": "NGC 5575"
            },
            {
              "ns": 0,
              "title": "NGC 5584"
            },
            {
              "ns": 0,
              "title": "NGC 5619"
            },
            {
              "ns": 0,
              "title": "NGC 5634"
            },
            {
              "ns": 0,
              "title": "NGC 5668"
            },
            {
              "ns": 0,
              "title": "NGC 5674"
            },
            {
              "ns": 0,
              "title": "NGC 5679 Group"
            },
            {
              "ns": 0,
              "title": "NGC 5701"
            },
            {
              "ns": 0,
              "title": "NGC 5705"
            },
            {
              "ns": 0,
              "title": "NGC 5713"
            },
            {
              "ns": 0,
              "title": "NGC 5719"
            },
            {
              "ns": 0,
              "title": "NGC 5746"
            },
            {
              "ns": 0,
              "title": "NGC 5750"
            },
            {
              "ns": 0,
              "title": "NGC 5765"
            },
            {
              "ns": 0,
              "title": "NGC 5774"
            },
            {
              "ns": 0,
              "title": "NGC 5775"
            },
            {
              "ns": 0,
              "title": "NGC 5806"
            },
            {
              "ns": 0,
              "title": "NGC 5838"
            },
            {
              "ns": 0,
              "title": "NGC 5846"
            },
            {
              "ns": 0,
              "title": "NGC 5850"
            },
            {
              "ns": 0,
              "title": "NY Virginis"
            },
            {
              "ns": 0,
              "title": "Near Infrared Camera and Multi-Object Spectrometer"
            },
            {
              "ns": 0,
              "title": "Nebula"
            },
            {
              "ns": 0,
              "title": "New General Catalogue"
            },
            {
              "ns": 0,
              "title": "North Polar Spur"
            },
            {
              "ns": 0,
              "title": "Nu Virginis"
            },
            {
              "ns": 0,
              "title": "Omega Virginis"
            },
            {
              "ns": 0,
              "title": "Omicron Virginis"
            },
            {
              "ns": 0,
              "title": "PG 1159-035"
            },
            {
              "ns": 0,
              "title": "PG 1216+069"
            },
            {
              "ns": 0,
              "title": "PKS 1148−001"
            },
            {
              "ns": 0,
              "title": "PKS 1302−102"
            },
            {
              "ns": 0,
              "title": "PKS 1335−127"
            },
            {
              "ns": 0,
              "title": "PKS 1402+044"
            },
            {
              "ns": 0,
              "title": "PKS 1502+036"
            },
            {
              "ns": 0,
              "title": "POX 186"
            },
            {
              "ns": 0,
              "title": "PSR B1257+12"
            },
            {
              "ns": 0,
              "title": "PSR B1257+12 A"
            },
            {
              "ns": 0,
              "title": "PSR B1257+12 B"
            },
            {
              "ns": 0,
              "title": "PSR B1257+12 C"
            },
            {
              "ns": 0,
              "title": "Pea galaxy"
            },
            {
              "ns": 0,
              "title": "Peculiar galaxy"
            },
            {
              "ns": 0,
              "title": "Phi Virginis"
            },
            {
              "ns": 0,
              "title": "Photometric redshift"
            },
            {
              "ns": 0,
              "title": "Pi Virginis"
            },
            {
              "ns": 0,
              "title": "Polar-ring galaxy"
            },
            {
              "ns": 0,
              "title": "Protogalaxy"
            },
            {
              "ns": 0,
              "title": "Psi Virginis"
            },
            {
              "ns": 0,
              "title": "Q1208+1011"
            },
            {
              "ns": 0,
              "title": "QS Virginis"
            },
            {
              "ns": 0,
              "title": "Qatar-2"
            },
            {
              "ns": 0,
              "title": "Quasar"
            },
            {
              "ns": 0,
              "title": "RT Virginis"
            },
            {
              "ns": 0,
              "title": "RX J1242−11"
            },
            {
              "ns": 0,
              "title": "RX J1347.5−1145"
            },
            {
              "ns": 0,
              "title": "R Virginis"
            },
            {
              "ns": 0,
              "title": "Radial velocity"
            },
            {
              "ns": 0,
              "title": "Radio galaxy"
            },
            {
              "ns": 0,
              "title": "Red nugget"
            },
            {
              "ns": 0,
              "title": "Redshift"
            },
            {
              "ns": 0,
              "title": "Rho Virginis"
            },
            {
              "ns": 0,
              "title": "Right ascension"
            },
            {
              "ns": 0,
              "title": "Ring galaxy"
            },
            {
              "ns": 0,
              "title": "Ross 128"
            },
            {
              "ns": 0,
              "title": "Ross 128 b"
            },
            {
              "ns": 0,
              "title": "Ross 458"
            },
            {
              "ns": 0,
              "title": "SDSS J1228+1040"
            },
            {
              "ns": 0,
              "title": "SDSS J1229+1122"
            },
            {
              "ns": 0,
              "title": "SDSS J1254+0846"
            },
            {
              "ns": 0,
              "title": "SDSS J150904.22+043441.8"
            },
            {
              "ns": 0,
              "title": "SN 1961I"
            },
            {
              "ns": 0,
              "title": "SN 1990N"
            },
            {
              "ns": 0,
              "title": "SN 1994D"
            },
            {
              "ns": 0,
              "title": "SN 2002cx"
            },
            {
              "ns": 0,
              "title": "SN 2007bi"
            },
            {
              "ns": 0,
              "title": "SN 2020fqv"
            },
            {
              "ns": 0,
              "title": "SN 2020jfo"
            },
            {
              "ns": 0,
              "title": "SS Virginis"
            },
            {
              "ns": 0,
              "title": "SW Virginis"
            },
            {
              "ns": 0,
              "title": "S Virginis"
            },
            {
              "ns": 0,
              "title": "Satellite galaxy"
            },
            {
              "ns": 0,
              "title": "Seyfert galaxy"
            },
            {
              "ns": 0,
              "title": "Sigma Virginis"
            },
            {
              "ns": 0,
              "title": "Solar mass"
            },
            {
              "ns": 0,
              "title": "Sombrero Galaxy"
            },
            {
              "ns": 0,
              "title": "Speca"
            },
            {
              "ns": 0,
              "title": "Speed of light"
            },
            {
              "ns": 0,
              "title": "Spica"
            },
            {
              "ns": 0,
              "title": "Spiral galaxy"
            },
            {
              "ns": 0,
              "title": "Spitzer Space Telescope"
            },
            {
              "ns": 0,
              "title": "Star"
            },
            {
              "ns": 0,
              "title": "Star cluster"
            },
            {
              "ns": 0,
              "title": "Starburst galaxies"
            },
            {
              "ns": 0,
              "title": "Starburst galaxy"
            },
            {
              "ns": 0,
              "title": "Stellar kinematics"
            },
            {
              "ns": 0,
              "title": "Stellar population"
            },
            {
              "ns": 0,
              "title": "Supercluster"
            },
            {
              "ns": 0,
              "title": "Supermassive black hole"
            },
            {
              "ns": 0,
              "title": "TXS 1321+045"
            },
            {
              "ns": 0,
              "title": "Tau Virginis"
            },
            {
              "ns": 0,
              "title": "Theta Virginis"
            },
            {
              "ns": 0,
              "title": "Thick disk"
            },
            {
              "ns": 0,
              "title": "Thin disk"
            },
            {
              "ns": 0,
              "title": "Transient astronomical event"
            },
            {
              "ns": 0,
              "title": "Type-cD galaxy"
            },
            {
              "ns": 0,
              "title": "U1.11"
            },
            {
              "ns": 0,
              "title": "UDFy-38135539"
            },
            {
              "ns": 0,
              "title": "UGC 6665"
            },
            {
              "ns": 0,
              "title": "UGC 8153"
            },
            {
              "ns": 0,
              "title": "ULAS J133553.45+113005.2"
            },
            {
              "ns": 0,
              "title": "ULIRG"
            },
            {
              "ns": 0,
              "title": "Ultra diffuse galaxy"
            },
            {
              "ns": 0,
              "title": "Ultramassive black hole"
            },
            {
              "ns": 0,
              "title": "Unbarred lenticular galaxy"
            },
            {
              "ns": 0,
              "title": "Unbarred spiral galaxy"
            },
            {
              "ns": 0,
              "title": "Upsilon Virginis"
            },
            {
              "ns": 0,
              "title": "Variable star designation"
            },
            {
              "ns": 0,
              "title": "Virgo (constellation)"
            },
            {
              "ns": 0,
              "title": "Virgo Cluster"
            },
            {
              "ns": 0,
              "title": "Virgo I"
            },
            {
              "ns": 0,
              "title": "Virgo Stellar Stream"
            },
            {
              "ns": 0,
              "title": "Virgo constellation"
            },
            {
              "ns": 0,
              "title": "Virgo in Chinese astronomy"
            },
            {
              "ns": 0,
              "title": "Visible light"
            },
            {
              "ns": 0,
              "title": "Void (astronomy)"
            },
            {
              "ns": 0,
              "title": "Void galaxy"
            },
            {
              "ns": 0,
              "title": "WASP-107"
            },
            {
              "ns": 0,
              "title": "WASP-107b"
            },
            {
              "ns": 0,
              "title": "WASP-16"
            },
            {
              "ns": 0,
              "title": "WASP-16b"
            },
            {
              "ns": 0,
              "title": "WASP-24"
            },
            {
              "ns": 0,
              "title": "WASP-24b"
            },
            {
              "ns": 0,
              "title": "WASP-37"
            },
            {
              "ns": 0,
              "title": "WASP-39"
            },
            {
              "ns": 0,
              "title": "WASP-39b"
            },
            {
              "ns": 0,
              "title": "WASP-54"
            },
            {
              "ns": 0,
              "title": "WASP-55"
            },
            {
              "ns": 0,
              "title": "WASP-85 Ab"
            },
            {
              "ns": 0,
              "title": "WD 1145+017"
            },
            {
              "ns": 0,
              "title": "WD 1145+017 b"
            },
            {
              "ns": 0,
              "title": "W Virginis"
            },
            {
              "ns": 0,
              "title": "Wild's Triplet"
            },
            {
              "ns": 0,
              "title": "Wolf-Rayet galaxy"
            },
            {
              "ns": 0,
              "title": "Wolf 424"
            },
            {
              "ns": 0,
              "title": "Wolf 489"
            },
            {
              "ns": 0,
              "title": "X-shaped radio galaxy"
            },
            {
              "ns": 0,
              "title": "XX Virginis"
            },
            {
              "ns": 0,
              "title": "Xi Virginis"
            },
            {
              "ns": 0,
              "title": "Zeta Virginis"
            }
          ]
        }
      }
    },
    "limits": {
      "links": 500
    }
  },
  "cached_at": 1770330159.5038695
}