{
  "domain": "physics",
  "title": "NGC 4207",
  "url": "https://en.wikipedia.org/wiki/NGC_4207",
  "content": "NGC 4207 is a spiral galaxy located about 50 million light-years away in the constellation Virgo. The galaxy was discovered by astronomer Heinrich d'Arrest on March 23, 1865. NGC 4207 is a member of the Virgo Cluster.\n\n\n== See also ==\nList of NGC objects (4001–5000)\n\n\n== References ==\n\n\n== External links ==\n Media related to NGC 4207 at Wikimedia Commons\nNGC 4207 on WikiSky: DSS2, SDSS, GALEX, IRAS, Hydrogen α, X-Ray, Astrophoto, Sky Map, Articles and images",
  "links": [],
  "timestamp": 1770330240.1204605
}